{
  "__comment__": "This file was automatically created by mcresources",
  "type": "minecraft:block",
  "pools": [
    {
      "name": "loot_pool",
      "rolls": 1,
      "entries": [
        {
          "type": "minecraft:item",
          "name": "minecraft:gleamflower",
          "conditions": [
            {
              "condition": "minecraft:block_state_property",
              "block": "beneath:crop/gleamflower",
              "properties": {
                "age": "3"
              }
            }
          ]
        }
      ],
      "conditions": [
        {
          "condition": "minecraft:survives_explosion"
        }
      ]
    },
    {
      "name": "loot_pool",
      "rolls": 1,
      "entries": [
        {
          "type": "minecraft:item",
          "name": "beneath:seeds/gleamflower"
        }
      ],
      "conditions": [
        {
          "condition": "minecraft:survives_explosion"
        }
      ]
    }
  ]
}